unthermal/__init__.py
unthermal/controlsys.py
unthermal/identsys.py
unthermal/thermalsys.py
unthermal-0.1001.dist-info/LICENSE
unthermal-0.1001.dist-info/METADATA
unthermal-0.1001.dist-info/WHEEL
unthermal-0.1001.dist-info/top_level.txt
unthermal-0.1001.dist-info/RECORD
