Metadata-Version: 2.1
Name: unthermal
Version: 0.1001
Summary: unthermal is a package designed for interacting with a physical thermal plant via IoT technology.
Author-email: Leonardo Bermeo <lbermeoc@unal.edu.co>
Project-URL: Homepage, https://github.com/nebisman/UNThermal.git
Requires-Python: >=3.7
License-File: LICENSE
Requires-Dist: iottalk-paho-mqtt
Requires-Dist: control
Requires-Dist: numpy
Requires-Dist: matplotlib
Requires-Dist: scipy
